pulsar_spectra/__init__.py
pulsar_spectra/_version.py
pulsar_spectra/analysis.py
pulsar_spectra/catalogue.py
pulsar_spectra/load_data.py
pulsar_spectra/models.py
pulsar_spectra/spectral_fit.py
pulsar_spectra/catalogue_papers/Alam_2021.yaml
pulsar_spectra/catalogue_papers/Alam_2021_raw_to_yaml.py
pulsar_spectra/catalogue_papers/Aloisi_2019.yaml
pulsar_spectra/catalogue_papers/Bailes_1994.yaml
pulsar_spectra/catalogue_papers/Bailes_1997.yaml
pulsar_spectra/catalogue_papers/Bartel_1978.yaml
pulsar_spectra/catalogue_papers/Bartel_1978_raw_to_yaml.py
pulsar_spectra/catalogue_papers/Basu_2016.yaml
pulsar_spectra/catalogue_papers/Basu_2016_raw_to_yaml.py
pulsar_spectra/catalogue_papers/Basu_2018.yaml
pulsar_spectra/catalogue_papers/Bates_2011.yaml
pulsar_spectra/catalogue_papers/Bates_2011_raw_to_yaml.py
pulsar_spectra/catalogue_papers/Bell_2016.yaml
pulsar_spectra/catalogue_papers/Bell_2016_raw_to_yaml.py
pulsar_spectra/catalogue_papers/Bhat_2023.yaml
pulsar_spectra/catalogue_papers/Bhattacharyya_2016.yaml
pulsar_spectra/catalogue_papers/Biggs_1996.yaml
pulsar_spectra/catalogue_papers/Bilous_2016.yaml
pulsar_spectra/catalogue_papers/Bilous_2016_raw_to_yaml.py
pulsar_spectra/catalogue_papers/Bilous_2020.yaml
pulsar_spectra/catalogue_papers/Bilous_2020_raw_to_yaml.py
pulsar_spectra/catalogue_papers/Bondonneau_2020.yaml
pulsar_spectra/catalogue_papers/Bondonneau_2020_raw_to_yaml.py
pulsar_spectra/catalogue_papers/Bondonneau_2021.yaml
pulsar_spectra/catalogue_papers/Bondonneau_2021_raw_to_yaml.py
pulsar_spectra/catalogue_papers/Boyles_2013.yaml
pulsar_spectra/catalogue_papers/Brinkman_2018.yaml
pulsar_spectra/catalogue_papers/Camilo_1995.yaml
pulsar_spectra/catalogue_papers/Camilo_1996.yaml
pulsar_spectra/catalogue_papers/Champion_2005a.yaml
pulsar_spectra/catalogue_papers/Champion_2005b.yaml
pulsar_spectra/catalogue_papers/Champion_2008.yaml
pulsar_spectra/catalogue_papers/Crawford_2001.yaml
pulsar_spectra/catalogue_papers/Crawford_2007.yaml
pulsar_spectra-2.1.0.dist-info/licenses/LICENSE
pulsar_spectra-2.1.0.dist-info/METADATA
pulsar_spectra-2.1.0.dist-info/WHEEL
pulsar_spectra-2.1.0.dist-info/entry_points.txt
pulsar_spectra-2.1.0.dist-info/top_level.txt
pulsar_spectra-2.1.0.dist-info/RECORD
