Metadata-Version: 2.4
Name: pulsar-spectra
Version: 2.1.0
Summary: A simple interface to record pulsar's flux density measurements for a large number of papers and perform fitting of spectral models.
Author: Christopher Lee
Author-email: Nick Swainston <nickaswainston@gmail.com>
License: MIT License
Requires-Python: >=3.9
License-File: LICENSE
Requires-Dist: numpy<2,>=1.20
Requires-Dist: matplotlib>=3.6
Requires-Dist: psrqpy>=1.2.9
Requires-Dist: iminuit>=2.9
Requires-Dist: jacobi>=0.2
Requires-Dist: pyyaml>=3.10
Requires-Dist: pandas<2,>=1.4
Dynamic: license-file
